vissim2geojson/__init__.py
vissim2geojson/_model.py
vissim2geojson/pkg_configs.py
vissim2geojson/vissim2geojson.py
vissim2geojson-1.5.3.dist-info/LICENSE
vissim2geojson-1.5.3.dist-info/METADATA
vissim2geojson-1.5.3.dist-info/WHEEL
vissim2geojson-1.5.3.dist-info/top_level.txt
vissim2geojson-1.5.3.dist-info/RECORD
