Metadata-Version: 2.1
Name: vissim2geojson
Version: 1.5.3
Summary: Convert VISSIM files: .inpx to .geojson, .fzp and .fhz to csv.
Home-page: https://github.com/Xiangyongluo/vissim2wgs1984
Author: Mr. Xiangyong Luo
Author-email: luoxiangyong01@gmail.com
Classifier: Programming Language :: Python :: 3
Classifier: License :: OSI Approved :: MIT License
Classifier: Operating System :: OS Independent
Requires-Python: >=3.10
License-File: LICENSE
